AUTHORS.rst
CONTRIBUTING.rst
HISTORY.rst
LICENSE
MANIFEST.in
README.rst
setup.cfg
setup.py
docs/Makefile
docs/authors.rst
docs/conf.py
docs/contributing.rst
docs/history.rst
docs/index.rst
docs/installation.rst
docs/make.bat
docs/readme.rst
docs/usage.rst
geoscale/__init__.py
geoscale/cli.py
geoscale/geoscale.py
geoscale.egg-info/PKG-INFO
geoscale.egg-info/SOURCES.txt
geoscale.egg-info/dependency_links.txt
geoscale.egg-info/entry_points.txt
geoscale.egg-info/not-zip-safe
geoscale.egg-info/requires.txt
geoscale.egg-info/top_level.txt
tests/__init__.py
tests/test_geoscale.py